README.md
jphmm_tools/__init__.py
jphmm_tools/aligner.py
jphmm_tools/la_referencer.py
jphmm_tools/splitter.py
jphmm_tools/subtyper.py
jphmm_tools/data/HIV1.breakpoints
jphmm_tools/data/HXB2.fasta
jphmm_tools-0.1.4.dist-info/LICENSE
jphmm_tools-0.1.4.dist-info/METADATA
jphmm_tools-0.1.4.dist-info/WHEEL
jphmm_tools-0.1.4.dist-info/entry_points.txt
jphmm_tools-0.1.4.dist-info/top_level.txt
jphmm_tools-0.1.4.dist-info/RECORD
