Metadata-Version: 2.1
Name: jphmm-tools
Version: 0.1.4
Summary: Tools for extracting information from jpHMM (http://jphmm.gobics.de) output.
Home-page: https://github.com/evolbioinfo/jphmm_tools
Author: Anna Zhukova
Author-email: anna.zhukova@pasteur.fr
License: UNKNOWN
Keywords: jpHMM,HIV,subtyping,recombinants
Platform: UNKNOWN
Classifier: Development Status :: 3 - Alpha
Classifier: Environment :: Console
Classifier: Intended Audience :: Developers
Classifier: Topic :: Scientific/Engineering :: Bio-Informatics
Classifier: Topic :: Software Development
Classifier: Topic :: Software Development :: Libraries :: Python Modules
Requires-Dist: pandas
Requires-Dist: numpy
Requires-Dist: biopython
